LICENSE
MANIFEST.in
README.md
dev-requirements.txt
requirements.txt
setup.cfg
setup.py
test-requirements.txt
project.d/README.md
project.d/classifiers.txt
project.d/coverage.cfg
project.d/pylint.cfg
project.d/skeleton_module.py
project.d/skeleton_testmodule.py
src/confluencer/__init__.py
src/confluencer/__main__.py
src/confluencer/_compat.py
src/confluencer/config.py
src/confluencer.egg-info/PKG-INFO
src/confluencer.egg-info/SOURCES.txt
src/confluencer.egg-info/dependency_links.txt
src/confluencer.egg-info/entry_points.txt
src/confluencer.egg-info/not-zip-safe
src/confluencer.egg-info/requires.txt
src/confluencer.egg-info/top_level.txt
src/confluencer/api/__init__.py
src/confluencer/commands/__init__.py
src/confluencer/commands/help.py
src/confluencer/commands/pretty.py
src/confluencer/commands/remove.py
src/confluencer/commands/stats.py
src/confluencer/commands/tidy.py
src/confluencer/tools/__init__.py
src/confluencer/tools/content.py
src/confluencer/util/__init__.py