Metadata-Version: 1.1
Name: confluencer
Version: 0.1.0.dev148
Summary: Confluencer – A CLI tool to automate common Confluence maintenance tasks and content publishing.
Home-page: https://github.com/1and1/confluencer
Author: 1&1 Group
Author-email: git@1and1.com
License: Apache 2.0
Keywords: atlassian,confluence,wiki,cli,tool
Platform: UNKNOWN
Classifier: Development Status :: 4 - Beta
Classifier: Intended Audience :: Developers
Classifier: Intended Audience :: End Users/Desktop
Classifier: Intended Audience :: System Administrators
Classifier: License :: OSI Approved :: Apache Software License
Classifier: Operating System :: OS Independent
Classifier: Programming Language :: Python :: 3
Classifier: Programming Language :: Python :: 3.4
Classifier: Environment :: Console
Classifier: Topic :: Documentation
Classifier: Topic :: Internet :: WWW/HTTP :: Site Management
Classifier: Topic :: Office/Business :: Groupware
Classifier: Topic :: Utilities
